pydecipher/__init__.py
pydecipher/bytecode.py
pydecipher/main.py
pydecipher/remap.py
pydecipher/utils.py
pydecipher/artifact_types/__init__.py
pydecipher/artifact_types/pe.py
pydecipher/artifact_types/py2exe.py
pydecipher/artifact_types/pyc.py
pydecipher/artifact_types/pyinstaller.py
pydecipher/artifact_types/zip.py
tests/__init__.py
tests/conftest.py
tests/utils.py
pydecipher-1.0.0.dist-info/LICENSE
pydecipher-1.0.0.dist-info/METADATA
pydecipher-1.0.0.dist-info/WHEEL
pydecipher-1.0.0.dist-info/entry_points.txt
pydecipher-1.0.0.dist-info/top_level.txt
pydecipher-1.0.0.dist-info/RECORD
