Metadata-Version: 2.1
Name: pydecipher
Version: 1.0.0
Summary: Python un-freezing and bytecode extraction + analysis framework
Home-page: https://github.com/mitre/pydecipher
Author: The MITRE Corporation
Author-email: pydecipher@mitre.org
License: UNKNOWN
Platform: UNKNOWN
Classifier: Development Status :: 5 - Production/Stable
Classifier: Environment :: Console
Classifier: Intended Audience :: Information Technology
Classifier: Operating System :: OS Independent
Classifier: Programming Language :: Python :: 3 :: Only
Classifier: Programming Language :: Python :: 3.8
Classifier: Programming Language :: Python :: 3.9
Classifier: Topic :: Security
Classifier: Topic :: Software Development :: Code Generators
Classifier: Topic :: Software Development :: Disassemblers
Requires-Dist: xdis (>=5.0.8)
Requires-Dist: python-magic
Requires-Dist: argparse
Requires-Dist: six
Requires-Dist: pefile
Requires-Dist: uncompyle6
Requires-Dist: signify (>=0.3.0)
Requires-Dist: asn1crypto
Requires-Dist: pycrypto
Requires-Dist: textdistance
Requires-Dist: Pebble
Provides-Extra: dev
Requires-Dist: sphinx ; extra == 'dev'
Requires-Dist: sphinx-rtd-theme ; extra == 'dev'
Requires-Dist: towncrier ; extra == 'dev'
Requires-Dist: pytest ; extra == 'dev'
Requires-Dist: dataclasses ; extra == 'dev'
Requires-Dist: bump2version ; extra == 'dev'
Requires-Dist: black ; extra == 'dev'
Requires-Dist: pre-commit ; extra == 'dev'
Requires-Dist: flake8 ; extra == 'dev'
Requires-Dist: flake8-docstrings ; extra == 'dev'
Requires-Dist: restructuredtext-lint ; extra == 'dev'
Provides-Extra: docs
Requires-Dist: sphinx ; extra == 'docs'
Requires-Dist: sphinx-rtd-theme ; extra == 'docs'
Requires-Dist: towncrier ; extra == 'docs'
Provides-Extra: test
Requires-Dist: pytest ; extra == 'test'
Requires-Dist: dataclasses ; extra == 'test'
